command/__init__.py
command/clean.py
command/create.py
command/delete.py
command/filter.py
command/list.py
command/main.py
command/utils/__init__.py
command/utils/helpers.py
video_duplicate_remover-0.1.0.dist-info/LICENSE
video_duplicate_remover-0.1.0.dist-info/METADATA
video_duplicate_remover-0.1.0.dist-info/WHEEL
video_duplicate_remover-0.1.0.dist-info/entry_points.txt
video_duplicate_remover-0.1.0.dist-info/top_level.txt
video_duplicate_remover-0.1.0.dist-info/RECORD
