Metadata-Version: 2.1
Name: video-duplicate-remover
Version: 0.1.0
Summary: A video cleaning cli application
Home-page: https://github.com/caleberi/video-duplicate-remover
Author: caleb eri
Author-email: caleberioluwa@gmail.com
License: MIT
License-File: LICENSE
Requires-Dist: click
Requires-Dist: black
Requires-Dist: setup-cfg-fmt
Requires-Dist: setup-py-upgrade
